README.rst
setup.py
bin/opstacle
opstacle/__init__.py
opstacle/config.py
opstacle/rollup.py
opstacle/util.py
opstacle.egg-info/PKG-INFO
opstacle.egg-info/SOURCES.txt
opstacle.egg-info/dependency_links.txt
opstacle.egg-info/requires.txt
opstacle.egg-info/top_level.txt