Metadata-Version: 1.1
Name: opstacle
Version: 1.0.1
Summary: A dangerous and probably broken SMTP proxy that attempts to keep you sane
Home-page: https://github.com/ewdurbin/opstacle/
Author: Ernest W. Durbin III
Author-email: ewdurbin@gmail.com
License: MIT
Platform: UNKNOWN
Classifier: Environment :: No Input/Output (Daemon)
Classifier: License :: OSI Approved :: MIT License
Classifier: Intended Audience :: System Administrators
Classifier: Operating System :: OS Independent
Classifier: Programming Language :: Python
Classifier: Programming Language :: Python :: 2
Classifier: Topic :: Communications :: Email :: Filters
Classifier: Topic :: System :: Networking :: Monitoring
